LICENSE
README.md
setup.cfg
setup.py
dnevnikru/__init__.py
dnevnikru/dnevnikru.py
dnevnikru/exceptions.py
dnevnikru/parsers.py
dnevnikru/settings.py
dnevnikru.egg-info/PKG-INFO
dnevnikru.egg-info/SOURCES.txt
dnevnikru.egg-info/dependency_links.txt
dnevnikru.egg-info/requires.txt
dnevnikru.egg-info/top_level.txt