Metadata-Version: 2.1
Name: dnevnikru
Version: 1.3.1
Summary: dnevnik.ru parser
Home-page: https://github.com/paracosm17/dnevnikru
Author: paracosm17
Author-email: paracosm17@yandex.ru
License: Apache License 2.0
Platform: UNKNOWN
Classifier: Programming Language :: Python :: 3.7
Classifier: Programming Language :: Python :: 3.8
